[{
 "type":
 "schnitzler-tagebuch",
 "color":
 "#037a33",
 "filename":
 "entry__1889-08-05",
 "caption":
 "Tagebuch",
 "idno":
 "https://schnitzler-tagebuch.acdh.oeaw.ac.at/entry__1889-08-05.html",
 "head":
 "Tagebuch, 5. August 1889",
 "desc":
{"listPerson":
  [
{
 "persName":
 "Adele Spitzer",
 "ref":
 "person_20274"}],
 "listPlace":
  [
 {
 "placeName":
 "Bad Ischl",
 "ref":
 "pmb213"}
 ]
}
}, {
 "type":
 "schnitzler-orte",
 "color":
 "#045344",
 "filename":
 "entity/213/",
 "caption":
 "Aufenthaltsorte",
 "idno":
 "https://pmb.acdh.oeaw.ac.at/entity/213/",
 "head":
 "Bad Ischl"
}, {
 "type":
 "schnitzler-cmif",
 "subtype":
 "#j7685005-64da-4e31-99b6-b4641aa1628c",
 "color":
 "#654321",
 "caption":
 "Gedruckte Briefwechsel",
 "head":
 "Arthur Schnitzler an Marie Glümer, 5. 8. 1889",
 "source":
 "Arthur Schnitzler: Briefe 1875–1912. Hrsg. v. Therese Nickl u. Heinrich Schnitzler. Frankfurt am Main: S. Fischer 1981."
}] 