[{
 "type":
 "schnitzler-tagebuch",
 "color":
 "#037a33",
 "filename":
 "entry__1891-10-06",
 "caption":
 "Tagebuch",
 "idno":
 "https://schnitzler-tagebuch.acdh.oeaw.ac.at/entry__1891-10-06.html",
 "head":
 "Tagebuch, 6. Oktober 1891",
 "desc":
{"listPerson":
  [
{
 "persName":
 "Marie Glümer",
 "ref":
 "person_15485"}]
}
}, {
 "type":
 "schnitzler-briefe",
 "color":
 "#A63437",
 "filename":
 "L00042",
 "caption":
 "Briefe mit Autorinnen und Autoren",
 "idno":
 "https://schnitzler-briefe.acdh.oeaw.ac.at/L00042.html",
 "head":
 "Wilhelm Bölsche an Arthur Schnitzler, 6. 10. 1891",
 "desc":
{"listPerson":
  [
{
 "persName":
 "Wilhelm Bölsche",
 "ref":
 "pmb11061"},
 {
 "persName":
 "Julius Hart",
 "ref":
 "pmb3394"},
 {
 "persName":
 "Ernst von Wolzogen",
 "ref":
 "pmb13169"}],
 "listBibl":
  [
 {
 "title":
 "Freie Bühne für modernes Leben",
 "ref":
 "pmb36149"}
 ,  {
 "title":
 "Der Sohn. Aus den Papieren eines Arztes",
 "ref":
 "pmb30257"}
 ,  {
 "title":
 "Das Lumpengesindel",
 "ref":
 "pmb33690"}
 ],
 "listPlace":
  [
 {
 "placeName":
 "Berlin",
 "ref":
 "pmb168"}
 ,  {
 "placeName":
 "Wien",
 "ref":
 "pmb50"}
 ,  {
 "placeName":
 "Friedrichshagen",
 "ref":
 "pmb1275"}
 ,  {
 "placeName":
 "Peter-Hille-Straße",
 "ref":
 "pmb1276"}
 ]
}
}, {
 "type":
 "schnitzler-orte",
 "color":
 "#045344",
 "filename":
 "entity/50/",
 "caption":
 "Aufenthaltsorte",
 "idno":
 "https://pmb.acdh.oeaw.ac.at/entity/50/",
 "head":
 "Wien"
}] 