[{
 "type":
 "schnitzler-tagebuch",
 "color":
 "#037a33",
 "filename":
 "entry__1897-04-20",
 "caption":
 "Tagebuch",
 "idno":
 "https://schnitzler-tagebuch.acdh.oeaw.ac.at/entry__1897-04-20.html",
 "head":
 "Tagebuch, 20. April 1897",
 "desc":
{"listPerson":
  [
{
 "persName":
 "Sandor Rosenberg",
 "ref":
 "person_19377"}],
 "listPlace":
  [
 {
 "placeName":
 "Jardin des Plantes",
 "ref":
 "pmb90950"}
 ]
}
}, {
 "type":
 "schnitzler-orte",
 "color":
 "#045344",
 "filename":
 "entity/182/",
 "caption":
 "Aufenthaltsorte",
 "idno":
 "https://pmb.acdh.oeaw.ac.at/entity/182/",
 "head":
 "Paris"
}, {
 "type":
 "schnitzler-orte",
 "color":
 "#045344",
 "filename":
 "entity/592/",
 "caption":
 "Aufenthaltsorte",
 "idno":
 "https://pmb.acdh.oeaw.ac.at/entity/592/",
 "head":
 "rue de Maubeuge"
}] 