[{
 "type":
 "schnitzler-tagebuch",
 "color":
 "#037a33",
 "filename":
 "entry__1897-05-17",
 "caption":
 "Tagebuch",
 "idno":
 "https://schnitzler-tagebuch.acdh.oeaw.ac.at/entry__1897-05-17.html",
 "head":
 "Tagebuch, 17. Mai 1897",
 "desc":
{"listPerson":
  [
{
 "persName":
 "Paul Goldmann",
 "ref":
 "person_15529"},
 {
 "persName":
 "Marie Reinhard",
 "ref":
 "person_19150"},
 {
 "persName":
 "Theodor Wolff",
 "ref":
 "person_21450"}],
 "listBibl":
  [
 {
 "title":
 "Sterben. Novelle",
 "ref":
 "pmb30117"}
 ,  {
 "title":
 "Le dindon (Ehemänner!!)",
 "ref":
 "pmb77931"}
 ]
}
}, {
 "type":
 "schnitzler-briefe",
 "color":
 "#A63437",
 "filename":
 "L00677",
 "caption":
 "Briefe mit Autorinnen und Autoren",
 "idno":
 "https://schnitzler-briefe.acdh.oeaw.ac.at/L00677.html",
 "head":
 "Hugo von Hofmannsthal an Arthur Schnitzler, 17. 5. [1897]",
 "desc":
{"listPerson":
  [
{
 "persName":
 "Hugo von Hofmannsthal",
 "ref":
 "pmb11740"},
 {
 "persName":
 "Otto Brahm",
 "ref":
 "pmb10986"},
 {
 "persName":
 "Georg Hirschfeld",
 "ref":
 "pmb11701"}],
 "listPlace":
  [
 {
 "placeName":
 "Wien",
 "ref":
 "pmb50"}
 ,  {
 "placeName":
 "Paris",
 "ref":
 "pmb182"}
 ,  {
 "placeName":
 "London",
 "ref":
 "pmb224"}
 ,  {
 "placeName":
 "Dornbach",
 "ref":
 "pmb499"}
 ,  {
 "placeName":
 "Neuwaldegg",
 "ref":
 "pmb170"}
 ]
}
}, {
 "type":
 "schnitzler-orte",
 "color":
 "#045344",
 "filename":
 "entity/182/",
 "caption":
 "Aufenthaltsorte",
 "idno":
 "https://pmb.acdh.oeaw.ac.at/entity/182/",
 "head":
 "Paris"
}, {
 "type":
 "schnitzler-orte",
 "color":
 "#045344",
 "filename":
 "entity/592/",
 "caption":
 "Aufenthaltsorte",
 "idno":
 "https://pmb.acdh.oeaw.ac.at/entity/592/",
 "head":
 "rue de Maubeuge"
}] 