[{
 "type":
 "schnitzler-tagebuch",
 "color":
 "#037a33",
 "filename":
 "entry__1899-12-01",
 "caption":
 "Tagebuch",
 "idno":
 "https://schnitzler-tagebuch.acdh.oeaw.ac.at/entry__1899-12-01.html",
 "head":
 "Tagebuch, 1. Dezember 1899",
 "desc":
{"listPerson":
  [
{
 "persName":
 "Leopoldine Müller",
 "ref":
 "person_18303"},
 {
 "persName":
 "Anna Springer",
 "ref":
 "person_20293"},
 {
 "persName":
 "Irma Hoffmeister",
 "ref":
 "person_16281"}],
 "listBibl":
  [
 {
 "title":
 "Prinz Friedrich von Homburg",
 "ref":
 "pmb30029"}
 ]
}
}, {
 "type":
 "schnitzler-orte",
 "color":
 "#045344",
 "filename":
 "entity/50/",
 "caption":
 "Aufenthaltsorte",
 "idno":
 "https://pmb.acdh.oeaw.ac.at/entity/50/",
 "head":
 "Wien"
}, {
 "type":
 "schnitzler-orte",
 "color":
 "#045344",
 "filename":
 "entity/790/",
 "caption":
 "Aufenthaltsorte",
 "idno":
 "https://pmb.acdh.oeaw.ac.at/entity/790/",
 "head":
 "Tuchlauben"
}, {
 "type":
 "pmb",
 "color":
 "#9B5F98",
 "filename":
 "entity/141446/",
 "caption":
 "PMB",
 "idno":
 "https://pmb.acdh.oeaw.ac.at/entity/141446/",
 "head":
 "Aufführung Prinz Friedrich von Homburg, 1.12.1899",
 "desc":
{"listBibl":
  [
 {
 "title":
 "Prinz Friedrich von Homburg oder die Schlacht bei Fehrbellin",
 "ref":
 "pmb30029"}
 ],
 "listPerson":
  [
{
 "persName":
 "Adolf von Sonnenthal",
 "ref":
 "pmb12809"},
 {
 "persName":
 "Hedwig Bleibtreu",
 "ref":
 "pmb10959"},
 {
 "persName":
 "Lotte Medelsky",
 "ref":
 "pmb2252"},
 {
 "persName":
 "Josef Lewinsky",
 "ref":
 "pmb12061"},
 {
 "persName":
 "Josef Kainz",
 "ref":
 "pmb11851"},
 {
 "persName":
 "Bernhard Baumeister",
 "ref":
 "pmb6173"},
 {
 "persName":
 "Eduard Devrient",
 "ref":
 "pmb5150"},
 {
 "persName":
 "Max Paulsen",
 "ref":
 "pmb12399"},
 {
 "persName":
 "Oskar Gimnig",
 "ref":
 "pmb11438"},
 {
 "persName":
 "Otto Tressler",
 "ref":
 "pmb12971"}],
 "listPlace":
  [
 {
 "placeName":
 "Burgtheater",
 "ref":
 "pmb14"}
 ],
 "listOrg":
  [
 {
 "orgName":
 "Burgtheater",
 "ref":
 "pmb36247"}
 ]
}
}] 