[{
 "type":
 "schnitzler-tagebuch",
 "color":
 "#037a33",
 "filename":
 "entry__1903-09-27",
 "caption":
 "Tagebuch",
 "idno":
 "https://schnitzler-tagebuch.acdh.oeaw.ac.at/entry__1903-09-27.html",
 "head":
 "Tagebuch, 27. September 1903",
 "desc":
{"listBibl":
  [
 {
 "title":
 "Der einsame Weg. Schauspiel in fünf Akten",
 "ref":
 "pmb29985"}
 ],
 "listPlace":
  [
 {
 "placeName":
 "Weidlingbach",
 "ref":
 "pmb44394"}
 ]
}
}, {
 "type":
 "schnitzler-briefe",
 "color":
 "#A63437",
 "filename":
 "L01319",
 "caption":
 "Briefe mit Autorinnen und Autoren",
 "idno":
 "https://schnitzler-briefe.acdh.oeaw.ac.at/L01319.html",
 "head":
 "Hugo von Hofmannsthal an Arthur Schnitzler, 27. 9. [1903]",
 "desc":
{"listPerson":
  [
{
 "persName":
 "Hugo von Hofmannsthal",
 "ref":
 "pmb11740"},
 {
 "persName":
 "Hermann Bahr",
 "ref":
 "pmb10815"},
 {
 "persName":
 "Heinrich Schnitzler",
 "ref":
 "pmb12692"}],
 "listBibl":
  [
 {
 "title":
 "Arthur Schnitzler",
 "ref":
 "pmb30637"}
 ],
 "listPlace":
  [
 {
 "placeName":
 "Wien",
 "ref":
 "pmb50"}
 ]
}
}, {
 "type":
 "schnitzler-orte",
 "color":
 "#045344",
 "filename":
 "entity/50/",
 "caption":
 "Aufenthaltsorte",
 "idno":
 "https://pmb.acdh.oeaw.ac.at/entity/50/",
 "head":
 "Wien"
}, {
 "type":
 "schnitzler-bahr",
 "color":
 "#F9BD63",
 "filename":
 "L041444",
 "caption":
 "Schnitzler/Bahr",
 "idno":
 "https://schnitzler-bahr.acdh.oeaw.ac.at/L041444.html",
 "head":
 "Hofmannsthal an Schnitzler, 27. 9. [1903]",
 "desc":
{"listPerson":
  [
{
 "persName":
 "Hugo von Hofmannsthal",
 "ref":
 "pmb11740"},
 {
 "persName":
 "Hermann Bahr",
 "ref":
 "pmb10815"}],
 "listBibl":
  [
 {
 "title":
 "Arthur Schnitzler",
 "ref":
 "pmb30637"}
 ],
 "listPlace":
  [
 {
 "placeName":
 "Wien",
 "ref":
 "pmb50"}
 ]
}
}] 