[{
 "type":
 "schnitzler-tagebuch",
 "color":
 "#037a33",
 "filename":
 "entry__1904-03-06",
 "caption":
 "Tagebuch",
 "idno":
 "https://schnitzler-tagebuch.acdh.oeaw.ac.at/entry__1904-03-06.html",
 "head":
 "Tagebuch, 6. März 1904",
 "desc":
{"listPerson":
  [
{
 "persName":
 "Richard Dehmel",
 "ref":
 "person_14383"},
 {
 "persName":
 "Leo Van-Jung",
 "ref":
 "person_20925"},
 {
 "persName":
 "Arthur Kaufmann",
 "ref":
 "person_16770"},
 {
 "persName":
 "Franziska Mütter",
 "ref":
 "person_18320"},
 {
 "persName":
 "Josefine Rothenstein",
 "ref":
 "person_19424"}],
 "listBibl":
  [
 {
 "title":
 "Der Weg ins Freie. Roman",
 "ref":
 "pmb29923"}
 ],
 "listPlace":
  [
 {
 "placeName":
 "Grinzing",
 "ref":
 "pmb90771"}
 ,  {
 "placeName":
 "Bösendorfer-Saal",
 "ref":
 "pmb4"}
 ]
}
}, {
 "type":
 "schnitzler-briefe",
 "color":
 "#A63437",
 "filename":
 "L01378",
 "caption":
 "Briefe mit Autorinnen und Autoren",
 "idno":
 "https://schnitzler-briefe.acdh.oeaw.ac.at/L01378.html",
 "head":
 "Richard Dehmel an Arthur Schnitzler, [6. 3. 1904?]",
 "desc":
{"listPerson":
  [
{
 "persName":
 "Richard Dehmel",
 "ref":
 "pmb11148"},
 {
 "persName":
 "Peter Behrens",
 "ref":
 "pmb10869"}]
}
}, {
 "type":
 "schnitzler-orte",
 "color":
 "#045344",
 "filename":
 "entity/50/",
 "caption":
 "Aufenthaltsorte",
 "idno":
 "https://pmb.acdh.oeaw.ac.at/entity/50/",
 "head":
 "Wien"
}, {
 "type":
 "pmb",
 "color":
 "#9B5F98",
 "filename":
 "entity/50184/",
 "caption":
 "PMB",
 "idno":
 "https://pmb.acdh.oeaw.ac.at/entity/50184/",
 "head":
 "Vorlesung von Richard Dehmel, 6.3.1904",
 "desc":
{"listPerson":
  [
{
 "persName":
 "Richard Dehmel",
 "ref":
 "pmb11148"},
 {
 "persName":
 "Ida Dehmel",
 "ref":
 "pmb4358"},
 {
 "persName":
 "Hugo von Hofmannsthal",
 "ref":
 "pmb11740"},
 {
 "persName":
 "Gustav Mahler",
 "ref":
 "pmb12163"},
 {
 "persName":
 "Alma Maria Mahler",
 "ref":
 "pmb12160"},
 {
 "persName":
 "Olga Schnitzler",
 "ref":
 "pmb2173"},
 {
 "persName":
 "Gertrude von Hofmannsthal",
 "ref":
 "pmb2292"},
 {
 "persName":
 "Julie Wassermann",
 "ref":
 "pmb13058"},
 {
 "persName":
 "Jakob Wassermann",
 "ref":
 "pmb13055"},
 {
 "persName":
 "Ernest Van Dyck",
 "ref":
 "pmb43762"},
 {
 "persName":
 "Tilly Koenen",
 "ref":
 "pmb19489"},
 {
 "persName":
 "Stefan Zweig",
 "ref":
 "pmb13212"},
 {
 "persName":
 "Camill Hoffmann",
 "ref":
 "pmb11727"},
 {
 "persName":
 "Adolph Donath",
 "ref":
 "pmb2968"}],
 "listPlace":
  [
 {
 "placeName":
 "Bösendorfer-Saal",
 "ref":
 "pmb4"}
 ]
}
}, {
 "type":
 "kalliope-verbund",
 "color":
 "#003574",
 "caption":
 "Kalliope Verbundkatalog",
 "idno":
 "http://kalliope-verbund.info/DE-2498-HS00081077",
 "head":
 "Schnitzler, Arthur: Familie. Tragikomödie [Dramatisches] (Manuskripttitel)",
 "text":
 "3 Bl."
}] 