[{
 "type":
 "schnitzler-tagebuch",
 "color":
 "#037a33",
 "filename":
 "entry__1905-08-28",
 "caption":
 "Tagebuch",
 "idno":
 "https://schnitzler-tagebuch.acdh.oeaw.ac.at/entry__1905-08-28.html",
 "head":
 "Tagebuch, 28. August 1905",
 "desc":
{"listPerson":
  [
{
 "persName":
 "Johann Sebastian Bach",
 "ref":
 "person_13344"},
 {
 "persName":
 "Otto Brahm",
 "ref":
 "person_13913"},
 {
 "persName":
 "Max Reinhardt",
 "ref":
 "person_19154"},
 {
 "persName":
 "Paul Schlenther",
 "ref":
 "person_19724"},
 {
 "persName":
 "Agnes Sorma",
 "ref":
 "person_20219"}],
 "listBibl":
  [
 {
 "title":
 "Der Ruf des Lebens. Schauspiel in drei Akten",
 "ref":
 "pmb29905"}
 ,  {
 "title":
 "Zwischenspiel. Komödie in drei Akten",
 "ref":
 "pmb29903"}
 ],
 "listPlace":
  [
 {
 "placeName":
 "Wien",
 "ref":
 "pmb50"}
 ,  {
 "placeName":
 "Türkenschanzpark",
 "ref":
 "pmb113"}
 ]
}
}, {
 "type":
 "schnitzler-orte",
 "color":
 "#045344",
 "filename":
 "entity/50/",
 "caption":
 "Aufenthaltsorte",
 "idno":
 "https://pmb.acdh.oeaw.ac.at/entity/50/",
 "head":
 "Wien"
}] 