[{
 "type":
 "schnitzler-tagebuch",
 "color":
 "#037a33",
 "filename":
 "entry__1905-07-09",
 "caption":
 "Tagebuch",
 "idno":
 "https://schnitzler-tagebuch.acdh.oeaw.ac.at/entry__1905-07-09.html",
 "head":
 "Tagebuch, 9. Juli 1905",
 "desc":
{"listBibl":
  [
 {
 "title":
 "Der Ruf des Lebens. Schauspiel in drei Akten",
 "ref":
 "pmb29905"}
 ]
}
}, {
 "type":
 "schnitzler-orte",
 "color":
 "#045344",
 "filename":
 "entity/483/",
 "caption":
 "Aufenthaltsorte",
 "idno":
 "https://pmb.acdh.oeaw.ac.at/entity/483/",
 "head":
 "Reichenau an der Rax"
}, {
 "type":
 "schnitzler-orte",
 "color":
 "#045344",
 "filename":
 "entity/44982/",
 "caption":
 "Aufenthaltsorte",
 "idno":
 "https://pmb.acdh.oeaw.ac.at/entity/44982/",
 "head":
 "Kurhaus Rudolfsbad"
}] 