[{
 "type":
 "schnitzler-tagebuch",
 "color":
 "#037a33",
 "filename":
 "entry__1905-02-17",
 "caption":
 "Tagebuch",
 "idno":
 "https://schnitzler-tagebuch.acdh.oeaw.ac.at/entry__1905-02-17.html",
 "head":
 "Tagebuch, 17. Februar 1905",
 "desc":
{"listPerson":
  [
{
 "persName":
 "Gisela Frid",
 "ref":
 "person_15193"},
 {
 "persName":
 "Gustav Frid",
 "ref":
 "person_15194"},
 {
 "persName":
 "Rudolf Maria Holzapfel",
 "ref":
 "person_16337"},
 {
 "persName":
 "Louise Schnitzler",
 "ref":
 "person_19831"}],
 "listBibl":
  [
 {
 "title":
 "Das neue Lied",
 "ref":
 "pmb30655"}
 ,  {
 "title":
 "Der Weg ins Freie. Roman",
 "ref":
 "pmb29923"}
 ],
 "listPlace":
  [
 {
 "placeName":
 "Chile",
 "ref":
 "pmb48169"}
 ]
}
}, {
 "type":
 "schnitzler-orte",
 "color":
 "#045344",
 "filename":
 "entity/50/",
 "caption":
 "Aufenthaltsorte",
 "idno":
 "https://pmb.acdh.oeaw.ac.at/entity/50/",
 "head":
 "Wien"
}] 