[{
 "type":
 "schnitzler-tagebuch",
 "color":
 "#037a33",
 "filename":
 "entry__1907-03-03",
 "caption":
 "Tagebuch",
 "idno":
 "https://schnitzler-tagebuch.acdh.oeaw.ac.at/entry__1907-03-03.html",
 "head":
 "Tagebuch, 3. März 1907",
 "desc":
{"listPerson":
  [
{
 "persName":
 "Erna Fleischer",
 "ref":
 "person_15033"},
 {
 "persName":
 "W. Fred",
 "ref":
 "person_15158"},
 {
 "persName":
 "Grete Jacques",
 "ref":
 "person_16485"},
 {
 "persName":
 "Felix Salten",
 "ref":
 "person_19542"},
 {
 "persName":
 "Louise Schnitzler",
 "ref":
 "person_19831"}],
 "listBibl":
  [
 {
 "title":
 "Komtesse Mizzi oder Der Familientag",
 "ref":
 "pmb29931"}
 ,  {
 "title":
 "Der Leuchtkäfer",
 "ref":
 "pmb33752"}
 ,  {
 "title":
 "Liebelei. Schauspiel in drei Akten",
 "ref":
 "pmb29917"}
 ],
 "listPlace":
  [
 {
 "placeName":
 "New York City",
 "ref":
 "pmb44053"}
 ]
}
}, {
 "type":
 "schnitzler-orte",
 "color":
 "#045344",
 "filename":
 "entity/50/",
 "caption":
 "Aufenthaltsorte",
 "idno":
 "https://pmb.acdh.oeaw.ac.at/entity/50/",
 "head":
 "Wien"
}] 