[{
 "type":
 "schnitzler-tagebuch",
 "color":
 "#037a33",
 "filename":
 "entry__1908-03-29",
 "caption":
 "Tagebuch",
 "idno":
 "https://schnitzler-tagebuch.acdh.oeaw.ac.at/entry__1908-03-29.html",
 "head":
 "Tagebuch, 29. März 1908",
 "desc":
{"listPerson":
  [
{
 "persName":
 "Wilhelm Busch",
 "ref":
 "person_14088"},
 {
 "persName":
 "Vincenz Chiavacci",
 "ref":
 "person_14195"},
 {
 "persName":
 "Karl Schönherr",
 "ref":
 "person_19850"},
 {
 "persName":
 "Felix Speidel",
 "ref":
 "person_20242"},
 {
 "persName":
 "Ludwig Thoma",
 "ref":
 "person_20716"},
 {
 "persName":
 "Otto Tressler",
 "ref":
 "person_20803"}],
 "listBibl":
  [
 {
 "title":
 "Ein Abschied",
 "ref":
 "pmb33806"}
 ,  {
 "title":
 "Der Weg ins Freie. Roman",
 "ref":
 "pmb29923"}
 ],
 "listPlace":
  [
 {
 "placeName":
 "Döbling",
 "ref":
 "pmb64219"}
 ]
}
}, {
 "type":
 "schnitzler-orte",
 "color":
 "#045344",
 "filename":
 "entity/50/",
 "caption":
 "Aufenthaltsorte",
 "idno":
 "https://pmb.acdh.oeaw.ac.at/entity/50/",
 "head":
 "Wien"
}] 