[{
 "type":
 "schnitzler-tagebuch",
 "color":
 "#037a33",
 "filename":
 "entry__1908-12-27",
 "caption":
 "Tagebuch",
 "idno":
 "https://schnitzler-tagebuch.acdh.oeaw.ac.at/entry__1908-12-27.html",
 "head":
 "Tagebuch, 27. Dezember 1908",
 "desc":
{"listPerson":
  [
{
 "persName":
 "Cohen",
 "ref":
 "person_14249"},
 {
 "persName":
 "Felix Salten",
 "ref":
 "person_19542"},
 {
 "persName":
 "Julius Leisching",
 "ref":
 "person_17417"}],
 "listBibl":
  [
 {
 "title":
 "Der junge Medardus. Dramatische Historie in einem Vorspiel und fünf Aufzügen",
 "ref":
 "pmb29937"}
 ,  {
 "title":
 "Aus dem Tagebuch eines alten Wieners",
 "ref":
 "pmb78957"}
 ],
 "listPlace":
  [
 {
 "placeName":
 "Japan",
 "ref":
 "pmb318"}
 ,  {
 "placeName":
 "Hohe Warte",
 "ref":
 "pmb92292"}
 ]
}
}, {
 "type":
 "schnitzler-briefe",
 "color":
 "#A63437",
 "filename":
 "L01819",
 "caption":
 "Briefe mit Autorinnen und Autoren",
 "idno":
 "https://schnitzler-briefe.acdh.oeaw.ac.at/L01819.html",
 "head":
 "Olga Schnitzler an Richard Beer-Hofmann, [27.? 12. 1908]",
 "desc":
{"listPerson":
  [
{
 "persName":
 "Olga Schnitzler",
 "ref":
 "pmb2173"},
 {
 "persName":
 "Richard Beer-Hofmann",
 "ref":
 "pmb10863"},
 {
 "persName":
 "Louise Schnitzler",
 "ref":
 "pmb12701"},
 {
 "persName":
 "Paula Beer-Hofmann",
 "ref":
 "pmb10860"},
 {
 "persName":
 "Arthur Kaufmann",
 "ref":
 "pmb2496"},
 {
 "persName":
 "Leo Van-Jung",
 "ref":
 "pmb26392"},
 {
 "persName":
 "Jakob Wassermann",
 "ref":
 "pmb13055"},
 {
 "persName":
 "Julie Wassermann",
 "ref":
 "pmb13058"},
 {
 "persName":
 "Agnes Ulmann",
 "ref":
 "pmb27942"},
 {
 "persName":
 "Naëmah Beer-Hofmann",
 "ref":
 "pmb2534"},
 {
 "persName":
 "Mirjam Beer-Hofmann",
 "ref":
 "pmb2668"},
 {
 "persName":
 "Gabriel Beer-Hofmann",
 "ref":
 "pmb13923"},
 {
 "persName":
 "Siegfried Trebitsch",
 "ref":
 "pmb12968"}],
 "listPlace":
  [
 {
 "placeName":
 "Wien",
 "ref":
 "pmb50"}
 ,  {
 "placeName":
 "XVIII., Währing",
 "ref":
 "pmb68"}
 ,  {
 "placeName":
 "Hasenauerstraße",
 "ref":
 "pmb383"}
 ]
}
}, {
 "type":
 "schnitzler-orte",
 "color":
 "#045344",
 "filename":
 "entity/50/",
 "caption":
 "Aufenthaltsorte",
 "idno":
 "https://pmb.acdh.oeaw.ac.at/entity/50/",
 "head":
 "Wien"
}, {
 "type":
 "kalliope-verbund",
 "color":
 "#003574",
 "caption":
 "Kalliope Verbundkatalog",
 "idno":
 "http://kalliope-verbund.info/DE-2498-HS00037803",
 "head":
 "Kolar Wölfel, Marianne an Schnitzler, Arthur [Briefe]",
 "text":
 "3 Bl."
}] 