[{
 "type":
 "schnitzler-tagebuch",
 "color":
 "#037a33",
 "filename":
 "entry__1909-12-22",
 "caption":
 "Tagebuch",
 "idno":
 "https://schnitzler-tagebuch.acdh.oeaw.ac.at/entry__1909-12-22.html",
 "head":
 "Tagebuch, 22. Dezember 1909",
 "desc":
{"listPerson":
  [
{
 "persName":
 "Otto Brahm",
 "ref":
 "person_13913"},
 {
 "persName":
 "Paul Goldmann",
 "ref":
 "person_15529"},
 {
 "persName":
 "Robert Hirschfeld",
 "ref":
 "person_16228"},
 {
 "persName":
 "Josef Kainz",
 "ref":
 "person_16646"},
 {
 "persName":
 "Jacob Pollak",
 "ref":
 "person_18884"},
 {
 "persName":
 "Paul Schlenther",
 "ref":
 "person_19724"},
 {
 "persName":
 "Louise Schnitzler",
 "ref":
 "person_19831"},
 {
 "persName":
 "Gustav Schwarzkopf",
 "ref":
 "person_19986"},
 {
 "persName":
 "Richard Wengraf",
 "ref":
 "person_21236"},
 {
 "persName":
 "Arthur Kaufmann",
 "ref":
 "person_16770"}],
 "listBibl":
  [
 {
 "title":
 "Frau Beate und ihr Sohn. Novelle",
 "ref":
 "pmb32133"}
 ,  {
 "title":
 "Der junge Medardus. Dramatische Historie in einem Vorspiel und fünf Aufzügen",
 "ref":
 "pmb29937"}
 ,  {
 "title":
 "Der Weg ins Freie. Roman",
 "ref":
 "pmb29923"}
 ,  {
 "title":
 "Der G'wissenswurm",
 "ref":
 "pmb76759"}
 ]
}
}, {
 "type":
 "schnitzler-briefe",
 "color":
 "#A63437",
 "filename":
 "L01907",
 "caption":
 "Briefe mit Autorinnen und Autoren",
 "idno":
 "https://schnitzler-briefe.acdh.oeaw.ac.at/L01907.html",
 "head":
 "Arthur Schnitzler an Hermann Bahr, 22. 12. 1909",
 "desc":
{"listPerson":
  [
{
 "persName":
 "Hermann Bahr",
 "ref":
 "pmb10815"}],
 "listPlace":
  [
 {
 "placeName":
 "Wien",
 "ref":
 "pmb50"}
 ,  {
 "placeName":
 "Edmund-Weiß-Gasse",
 "ref":
 "pmb133"}
 ]
}
}, {
 "type":
 "schnitzler-orte",
 "color":
 "#045344",
 "filename":
 "entity/50/",
 "caption":
 "Aufenthaltsorte",
 "idno":
 "https://pmb.acdh.oeaw.ac.at/entity/50/",
 "head":
 "Wien"
}, {
 "type":
 "schnitzler-bahr",
 "color":
 "#F9BD63",
 "filename":
 "L041115",
 "caption":
 "Schnitzler/Bahr",
 "idno":
 "https://schnitzler-bahr.acdh.oeaw.ac.at/L041115.html",
 "head":
 "Schnitzler an Bahr, 22. 12. 1909",
 "desc":
{"listPerson":
  [
{
 "persName":
 "Hermann Bahr",
 "ref":
 "pmb10815"}],
 "listPlace":
  [
 {
 "placeName":
 "Wien",
 "ref":
 "pmb50"}
 ,  {
 "placeName":
 "Edmund-Weiß-Gasse",
 "ref":
 "pmb133"}
 ]
}
}, {
 "type":
 "schnitzler-cmif",
 "subtype":
 "#ya489e21-54d5-40de-a56d-f4548e894428",
 "color":
 "#654321",
 "caption":
 "Gedruckte Briefwechsel",
 "head":
 "Arthur Schnitzler an Otto Brahm, 22.12.1909",
 "source":
 "Der Briefwechsel Arthur Schnitzler – Otto Brahm. Vollständige Ausgabe. Hg., eingel. und erl. von Oskar Seidlin. Tübingen: Niemeyer, 1975."
}] 