[{
 "type":
 "schnitzler-tagebuch",
 "color":
 "#037a33",
 "filename":
 "entry__1910-07-16",
 "caption":
 "Tagebuch",
 "idno":
 "https://schnitzler-tagebuch.acdh.oeaw.ac.at/entry__1910-07-16.html",
 "head":
 "Tagebuch, 16. Juli 1910",
 "desc":
{"listPerson":
  [
{
 "persName":
 "Albert Bassermann",
 "ref":
 "person_13457"},
 {
 "persName":
 "Alfred von Berger",
 "ref":
 "person_13624"},
 {
 "persName":
 "Otto Brahm",
 "ref":
 "person_13913"},
 {
 "persName":
 "Ebeseder",
 "ref":
 "person_14601"},
 {
 "persName":
 "Albert Ehrenstein",
 "ref":
 "person_14643"},
 {
 "persName":
 "Paul Goldmann",
 "ref":
 "person_15529"},
 {
 "persName":
 "Felix Markbreiter",
 "ref":
 "person_17901"},
 {
 "persName":
 "Alfred Polgar",
 "ref":
 "person_18856"},
 {
 "persName":
 "Richard Rosenbaum",
 "ref":
 "person_19364"},
 {
 "persName":
 "Gustav Schwarzkopf",
 "ref":
 "person_19986"},
 {
 "persName":
 "Carl von Zeska",
 "ref":
 "person_21543"},
 {
 "persName":
 "Leo Feld",
 "ref":
 "person_14923"}],
 "listBibl":
  [
 {
 "title":
 "Das weite Land. Tragikomödie in fünf Akten",
 "ref":
 "pmb30207"}
 ,  {
 "title":
 "Der junge Medardus. Dramatische Historie in einem Vorspiel und fünf Aufzügen",
 "ref":
 "pmb29937"}
 ,  {
 "title":
 "Traumulus",
 "ref":
 "pmb31407"}
 ],
 "listPlace":
  [
 {
 "placeName":
 "Spöttelgasse",
 "ref":
 "pmb92539"}
 ,  {
 "placeName":
 "Burgtheater",
 "ref":
 "pmb14"}
 ,  {
 "placeName":
 "Kärntnerstraße",
 "ref":
 "pmb92330"}
 ]
}
}, {
 "type":
 "schnitzler-orte",
 "color":
 "#045344",
 "filename":
 "entity/50/",
 "caption":
 "Aufenthaltsorte",
 "idno":
 "https://pmb.acdh.oeaw.ac.at/entity/50/",
 "head":
 "Wien"
}, {
 "type":
 "schnitzler-traeume",
 "subtype":
 "#ISBN978-3-8353-1029-2",
 "color":
 "#1193CC",
 "caption":
 "Traumtagebuch",
 "head":
 "Traum vom 16. Juli 1910",
 "source":
 "Arthur Schnitzler: Träume. Das Traumtagebuch 1875–1931. Herausgegeben von Peter Michael Braunwarth und Leo A. Lensing. Göttingen: Wallstein 2012 (Bibliothek Janowitz, Bd. 20)"
}] 