[{
 "type":
 "schnitzler-tagebuch",
 "color":
 "#037a33",
 "filename":
 "entry__1910-03-27",
 "caption":
 "Tagebuch",
 "idno":
 "https://schnitzler-tagebuch.acdh.oeaw.ac.at/entry__1910-03-27.html",
 "head":
 "Tagebuch, 27. März 1910",
 "desc":
{"listPerson":
  [
{
 "persName":
 "Johann Sebastian Bach",
 "ref":
 "person_13344"},
 {
 "persName":
 "Heinrich Mann",
 "ref":
 "person_17834"},
 {
 "persName":
 "Heinrich Schnitzler",
 "ref":
 "person_19822"},
 {
 "persName":
 "Helene Schnitzler",
 "ref":
 "person_19823"},
 {
 "persName":
 "Julius Schnitzler",
 "ref":
 "person_19827"},
 {
 "persName":
 "Louise Schnitzler",
 "ref":
 "person_19831"},
 {
 "persName":
 "Karl Schönherr",
 "ref":
 "person_19850"},
 {
 "persName":
 "Hugo von Hofmannsthal",
 "ref":
 "person_16293"}],
 "listBibl":
  [
 {
 "title":
 "Frau Beate und ihr Sohn. Novelle",
 "ref":
 "pmb32133"}
 ,  {
 "title":
 "Der junge Medardus. Dramatische Historie in einem Vorspiel und fünf Aufzügen",
 "ref":
 "pmb29937"}
 ,  {
 "title":
 "Lucidor",
 "ref":
 "pmb76491"}
 ],
 "listPlace":
  [
 {
 "placeName":
 "Dornbacher Park",
 "ref":
 "pmb176"}
 ]
}
}, {
 "type":
 "schnitzler-orte",
 "color":
 "#045344",
 "filename":
 "entity/50/",
 "caption":
 "Aufenthaltsorte",
 "idno":
 "https://pmb.acdh.oeaw.ac.at/entity/50/",
 "head":
 "Wien"
}] 