[{
 "type":
 "schnitzler-tagebuch",
 "color":
 "#037a33",
 "filename":
 "entry__1915-12-24",
 "caption":
 "Tagebuch",
 "idno":
 "https://schnitzler-tagebuch.acdh.oeaw.ac.at/entry__1915-12-24.html",
 "head":
 "Tagebuch, 24. Dezember 1915",
 "desc":
{"listPerson":
  [
{
 "persName":
 "Eugenie Bachrach",
 "ref":
 "person_13355"},
 {
 "persName":
 "Stefanie Bachrach",
 "ref":
 "person_13359"},
 {
 "persName":
 "Markus Hajek",
 "ref":
 "person_15855"},
 {
 "persName":
 "Hans Schnitzler",
 "ref":
 "person_19821"},
 {
 "persName":
 "Heinrich Schnitzler",
 "ref":
 "person_19822"},
 {
 "persName":
 "Julius Schnitzler",
 "ref":
 "person_19827"},
 {
 "persName":
 "Karl Schnitzler",
 "ref":
 "person_19828"},
 {
 "persName":
 "Gustav Schwarzkopf",
 "ref":
 "person_19986"},
 {
 "persName":
 "Friederike Urbantschitsch",
 "ref":
 "person_20891"},
 {
 "persName":
 "Rudolf Urbantschitsch",
 "ref":
 "person_20892"},
 {
 "persName":
 "Marianne Giustiniani",
 "ref":
 "person_21600"},
 {
 "persName":
 "Max Leitner",
 "ref":
 "person_17425"},
 {
 "persName":
 "Arthur Kaufmann",
 "ref":
 "person_16770"},
 {
 "persName":
 "Rudolf Olden",
 "ref":
 "person_18548"},
 {
 "persName":
 "Frieda Pollak",
 "ref":
 "person_18881"}],
 "listBibl":
  [
 {
 "title":
 "Flucht in die Finsternis",
 "ref":
 "pmb30863"}
 ],
 "listPlace":
  [
 {
 "placeName":
 "Bulgarien",
 "ref":
 "pmb249"}
 ,  {
 "placeName":
 "Wiener Neustadt",
 "ref":
 "pmb92109"}
 ,  {
 "placeName":
 "Budapest",
 "ref":
 "pmb43471"}
 ]
}
}, {
 "type":
 "schnitzler-orte",
 "color":
 "#045344",
 "filename":
 "entity/50/",
 "caption":
 "Aufenthaltsorte",
 "idno":
 "https://pmb.acdh.oeaw.ac.at/entity/50/",
 "head":
 "Wien"
}] 