[{
 "type":
 "schnitzler-tagebuch",
 "color":
 "#037a33",
 "filename":
 "entry__1915-12-21",
 "caption":
 "Tagebuch",
 "idno":
 "https://schnitzler-tagebuch.acdh.oeaw.ac.at/entry__1915-12-21.html",
 "head":
 "Tagebuch, 21. Dezember 1915",
 "desc":
{"listPerson":
  [
{
 "persName":
 "Ludwig Fulda",
 "ref":
 "person_15306"},
 {
 "persName":
 "Charles Leyst",
 "ref":
 "person_17499"},
 {
 "persName":
 "Carl Meinhard",
 "ref":
 "person_18047"},
 {
 "persName":
 "Dora Kallmus",
 "ref":
 "person_18573"},
 {
 "persName":
 "Alice Schmutzer",
 "ref":
 "person_19783"},
 {
 "persName":
 "Heinrich Schnitzler",
 "ref":
 "person_19822"},
 {
 "persName":
 "Anton Wildgans",
 "ref":
 "person_21328"},
 {
 "persName":
 "Mattia Battistini",
 "ref":
 "person_13462"},
 {
 "persName":
 "Harry Walden",
 "ref":
 "person_21059"},
 {
 "persName":
 "Georges Danton",
 "ref":
 "person_14356"},
 {
 "persName":
 "Adolf Gelber",
 "ref":
 "person_15375"}],
 "listBibl":
  [
 {
 "title":
 "Danton",
 "ref":
 "pmb78963"}
 ,  {
 "title":
 "Don Juan’s Mission. Drama in drei Akten",
 "ref":
 "pmb78964"}
 ],
 "listPlace":
  [
 {
 "placeName":
 "Burgtheater",
 "ref":
 "pmb14"}
 ,  {
 "placeName":
 "Deutsches Volkstheater",
 "ref":
 "pmb92202"}
 ,  {
 "placeName":
 "Schlachtensee",
 "ref":
 "pmb54921"}
 ]
}
}, {
 "type":
 "schnitzler-orte",
 "color":
 "#045344",
 "filename":
 "entity/50/",
 "caption":
 "Aufenthaltsorte",
 "idno":
 "https://pmb.acdh.oeaw.ac.at/entity/50/",
 "head":
 "Wien"
}] 