[{
 "type":
 "schnitzler-tagebuch",
 "color":
 "#037a33",
 "filename":
 "entry__1916-10-25",
 "caption":
 "Tagebuch",
 "idno":
 "https://schnitzler-tagebuch.acdh.oeaw.ac.at/entry__1916-10-25.html",
 "head":
 "Tagebuch, 25. Oktober 1916",
 "desc":
{"listPerson":
  [
{
 "persName":
 "Hans Müller",
 "ref":
 "person_18297"},
 {
 "persName":
 "Franz Steiner",
 "ref":
 "person_20372"},
 {
 "persName":
 "Ludwig Uhland",
 "ref":
 "person_20856"}],
 "listBibl":
  [
 {
 "title":
 "Die Schwestern oder Casanova in Spa. Lustspiel in Versen",
 "ref":
 "pmb30819"}
 ,  {
 "title":
 "Könige",
 "ref":
 "pmb31625"}
 ,  {
 "title":
 "Ludwig der Bayer",
 "ref":
 "pmb81433"}
 ]
}
}, {
 "type":
 "schnitzler-orte",
 "color":
 "#045344",
 "filename":
 "entity/50/",
 "caption":
 "Aufenthaltsorte",
 "idno":
 "https://pmb.acdh.oeaw.ac.at/entity/50/",
 "head":
 "Wien"
}] 