[{
 "type":
 "schnitzler-tagebuch",
 "color":
 "#037a33",
 "filename":
 "entry__1919-04-24",
 "caption":
 "Tagebuch",
 "idno":
 "https://schnitzler-tagebuch.acdh.oeaw.ac.at/entry__1919-04-24.html",
 "head":
 "Tagebuch, 24. April 1919",
 "desc":
{"listPerson":
  [
{
 "persName":
 "Irmgard Kaufmann",
 "ref":
 "person_16449"},
 {
 "persName":
 "Georg Kaiser",
 "ref":
 "person_16650"},
 {
 "persName":
 "Albert von Mensdorff-Pouilly-Dietrichstein",
 "ref":
 "person_18079"},
 {
 "persName":
 "Berta Zuckerkandl",
 "ref":
 "person_21594"},
 {
 "persName":
 "Siegmund von Sonnenthal",
 "ref":
 "person_20209"}],
 "listBibl":
  [
 {
 "title":
 "Der Gang zum Weiher. Dramatische Dichtung",
 "ref":
 "pmb30775"}
 ,  {
 "title":
 "Die Sorina",
 "ref":
 "pmb78885"}
 ],
 "listPlace":
  [
 {
 "placeName":
 "Pötzleinsdorf",
 "ref":
 "pmb169"}
 ]
}
}, {
 "type":
 "schnitzler-orte",
 "color":
 "#045344",
 "filename":
 "entity/50/",
 "caption":
 "Aufenthaltsorte",
 "idno":
 "https://pmb.acdh.oeaw.ac.at/entity/50/",
 "head":
 "Wien"
}] 