[{
 "type":
 "schnitzler-tagebuch",
 "color":
 "#037a33",
 "filename":
 "entry__1921-02-15",
 "caption":
 "Tagebuch",
 "idno":
 "https://schnitzler-tagebuch.acdh.oeaw.ac.at/entry__1921-02-15.html",
 "head":
 "Tagebuch, 15. Februar 1921",
 "desc":
{"listPerson":
  [
{
 "persName":
 "Robert Michel",
 "ref":
 "person_18147"},
 {
 "persName":
 "Arthur Stern",
 "ref":
 "person_20405"},
 {
 "persName":
 "Ruth Lindberg",
 "ref":
 "person_17562"},
 {
 "persName":
 "Napoleon Bonaparte",
 "ref":
 "person_18356"}],
 "listBibl":
  [
 {
 "title":
 "Der Gang zum Weiher. Dramatische Dichtung",
 "ref":
 "pmb30775"}
 ,  {
 "title":
 "Liebelei. Schauspiel in drei Akten",
 "ref":
 "pmb29917"}
 ,  {
 "title":
 "Der junge Medardus",
 "ref":
 "pmb32294"}
 ]
}
}, {
 "type":
 "schnitzler-orte",
 "color":
 "#045344",
 "filename":
 "entity/50/",
 "caption":
 "Aufenthaltsorte",
 "idno":
 "https://pmb.acdh.oeaw.ac.at/entity/50/",
 "head":
 "Wien"
}] 