[{
 "type":
 "schnitzler-tagebuch",
 "color":
 "#037a33",
 "filename":
 "entry__1921-06-14",
 "caption":
 "Tagebuch",
 "idno":
 "https://schnitzler-tagebuch.acdh.oeaw.ac.at/entry__1921-06-14.html",
 "head":
 "Tagebuch, 14. Juni 1921",
 "desc":
{"listPerson":
  [
{
 "persName":
 "Lili Schnitzler",
 "ref":
 "person_14130"},
 {
 "persName":
 "Gisela Hajek",
 "ref":
 "person_15854"},
 {
 "persName":
 "Rudolf Lankus",
 "ref":
 "person_17320"},
 {
 "persName":
 "Adolph L’Arronge",
 "ref":
 "person_17331"},
 {
 "persName":
 "Richard Rosenbaum",
 "ref":
 "person_19364"},
 {
 "persName":
 "Heinrich Schnitzler",
 "ref":
 "person_19822"},
 {
 "persName":
 "Julius Schnitzler",
 "ref":
 "person_19827"},
 {
 "persName":
 "George Bernard Shaw",
 "ref":
 "person_20080"},
 {
 "persName":
 "Stendhal",
 "ref":
 "person_20397"},
 {
 "persName":
 "Eduard Weber",
 "ref":
 "person_21121"},
 {
 "persName":
 "Anton Wildgans",
 "ref":
 "person_21328"}],
 "listBibl":
  [
 {
 "title":
 "Der Weg ins Freie. Roman",
 "ref":
 "pmb29923"}
 ,  {
 "title":
 "Mein Leopold",
 "ref":
 "pmb62775"}
 ,  {
 "title":
 "Helden",
 "ref":
 "pmb29963"}
 ,  {
 "title":
 "Le rouge et le noir. Chronique du XIXe siècle",
 "ref":
 "pmb77822"}
 ],
 "listPlace":
  [
 {
 "placeName":
 "Bad Gastein",
 "ref":
 "pmb521"}
 ]
}
}, {
 "type":
 "schnitzler-orte",
 "color":
 "#045344",
 "filename":
 "entity/50/",
 "caption":
 "Aufenthaltsorte",
 "idno":
 "https://pmb.acdh.oeaw.ac.at/entity/50/",
 "head":
 "Wien"
}] 