[{
 "type":
 "Arthur-Schnitzler-digital",
 "color":
 "#801e23",
 "caption":
 "Arthur Schnitzler digital (Werke 1905–1931)",
 "idno":
 "https://www.schnitzler-edition.net/Dokumentarisch/Dokumentklasse/ELS_T1_0185",
 "head":
 "Fräulein Else, msl. Werkniederschrift"
}, {
 "type":
 "schnitzler-tagebuch",
 "color":
 "#037a33",
 "filename":
 "entry__1923-04-18",
 "caption":
 "Tagebuch",
 "idno":
 "https://schnitzler-tagebuch.acdh.oeaw.ac.at/entry__1923-04-18.html",
 "head":
 "Tagebuch, 18. April 1923",
 "desc":
{"listPerson":
  [
{
 "persName":
 "Catherine Barjanski",
 "ref":
 "person_13424"},
 {
 "persName":
 "Franz Werfel",
 "ref":
 "person_21243"}],
 "listBibl":
  [
 {
 "title":
 "Aphoristisches",
 "ref":
 "pmb35745"}
 ,  {
 "title":
 "Fräulein Else",
 "ref":
 "pmb29941"}
 ,  {
 "title":
 "Schweiger",
 "ref":
 "pmb32019"}
 ]
}
}, {
 "type":
 "schnitzler-orte",
 "color":
 "#045344",
 "filename":
 "entity/39615/",
 "caption":
 "Aufenthaltsorte",
 "idno":
 "https://pmb.acdh.oeaw.ac.at/entity/39615/",
 "head":
 "Bratislava"
}, {
 "type":
 "kalliope-verbund",
 "color":
 "#003574",
 "caption":
 "Kalliope Verbundkatalog",
 "idno":
 "http://kalliope-verbund.info/DE-2498-HS00074955",
 "head":
 "Soergel, Albert an Schnitzler, Arthur [Briefe]",
 "text":
 "1 Bl.",
 "desc":
{"listPerson":
  [
{
 "persName":
 "Albert (1880-1958) Soergel",
 "ref":
 "http://d-nb.info/gnd/117452580"},
 {
 "persName":
 "Gesellschaft der Bücherfreunde &lt;Chemnitz&gt;",
 "ref":
 "http://d-nb.info/gnd/252889-7"}]
}
}] 