[{
 "type":
 "schnitzler-tagebuch",
 "color":
 "#037a33",
 "filename":
 "entry__1928-07-11",
 "caption":
 "Tagebuch",
 "idno":
 "https://schnitzler-tagebuch.acdh.oeaw.ac.at/entry__1928-07-11.html",
 "head":
 "Tagebuch, 11. Juli 1928",
 "desc":
{"listPerson":
  [
{
 "persName":
 "Richard Beer-Hofmann",
 "ref":
 "person_13551"},
 {
 "persName":
 "Clara Katharina Pollaczek",
 "ref":
 "person_18863"},
 {
 "persName":
 "Karl Pollak",
 "ref":
 "person_18887"},
 {
 "persName":
 "Heinrich Schnitzler",
 "ref":
 "person_19822"},
 {
 "persName":
 "Gustav Schwarzkopf",
 "ref":
 "person_19986"},
 {
 "persName":
 "Franz Horch",
 "ref":
 "person_16355"},
 {
 "persName":
 "Ruth Lindberg",
 "ref":
 "person_17562"},
 {
 "persName":
 "Paula Beer-Hofmann",
 "ref":
 "person_13550"},
 {
 "persName":
 "Alois Böhm",
 "ref":
 "person_13830"}],
 "listBibl":
  [
 {
 "title":
 "Zug der Schatten",
 "ref":
 "pmb32049"}
 ,  {
 "title":
 "Iphigenie auf Tauris",
 "ref":
 "pmb32951"}
 ],
 "listPlace":
  [
 {
 "placeName":
 "Graben",
 "ref":
 "pmb90753"}
 ,  {
 "placeName":
 "Salzburg",
 "ref":
 "pmb30"}
 ]
}
}, {
 "type":
 "schnitzler-orte",
 "color":
 "#045344",
 "filename":
 "entity/50/",
 "caption":
 "Aufenthaltsorte",
 "idno":
 "https://pmb.acdh.oeaw.ac.at/entity/50/",
 "head":
 "Wien"
}, {
 "type":
 "schnitzler-orte",
 "color":
 "#045344",
 "filename":
 "entity/90753/",
 "caption":
 "Aufenthaltsorte",
 "idno":
 "https://pmb.acdh.oeaw.ac.at/entity/90753/",
 "head":
 "Graben"
}, {
 "type":
 "pollaczek",
 "color":
 "#1e81b0",
 "filename":
 "ckp554",
 "caption":
 "Pollazczek: Schnitzler und ich",
 "idno":
 "https://pollaczek.acdh.oeaw.ac.at/ckp554.html",
 "head":
 "Tagebuch von Clara Katharina Pollaczek, 10.–17. Juli 1928"
}, {
 "type":
 "kalliope-verbund",
 "color":
 "#003574",
 "caption":
 "Kalliope Verbundkatalog",
 "idno":
 "http://kalliope-verbund.info/DE-2498-HS00038045",
 "head":
 "Korger, Friedrich an Bettelheim, Anton [Briefe]",
 "text":
 "2 Bl. mit Antwort von Bettelheim",
 "desc":
{"listPerson":
  [
{
 "persName":
 "Anton (1851-1930) Bettelheim",
 "ref":
 "http://d-nb.info/gnd/116155795"}]
}
}] 